matchutils/__init__.py
matchutils/_matchutils.py
matchutils-0.0.1.dist-info/LICENSE
matchutils-0.0.1.dist-info/METADATA
matchutils-0.0.1.dist-info/WHEEL
matchutils-0.0.1.dist-info/top_level.txt
matchutils-0.0.1.dist-info/RECORD
