Metadata-Version: 2.1
Name: matchutils
Version: 0.0.1
Summary: extensions for python's match/case statement
Home-page: https://gitlab.com/thomasjlsn/matchutils
Author: Thomas Ellison
Author-email: thomasjlsn@gmail.com
License-File: LICENSE
